wallbox/__init__.py
wallbox/bearerauth.py
wallbox/statuses.py
wallbox/wallbox.py
wallbox-0.8.0.dist-info/LICENSE
wallbox-0.8.0.dist-info/METADATA
wallbox-0.8.0.dist-info/WHEEL
wallbox-0.8.0.dist-info/top_level.txt
wallbox-0.8.0.dist-info/RECORD
