Metadata-Version: 2.2
Name: wallbox
Version: 0.8.0
Summary: Module for interacting with Wallbox EV charger api
Home-page: https://github.com/cliviu74/wallbox
Author: Liviu Chiribuca
Author-email: cliviu74@yahoo.com
License: Apache 2
Classifier: Programming Language :: Python :: 3
Requires-Python: >=3.7
License-File: LICENSE
Requires-Dist: requests>=2.22.0
Requires-Dist: aenum>=3.1.8
Dynamic: author
Dynamic: author-email
Dynamic: classifier
Dynamic: description
Dynamic: description-content-type
Dynamic: home-page
Dynamic: keywords
Dynamic: license
Dynamic: requires-dist
Dynamic: requires-python
Dynamic: summary
